odoo/addons/stock_packaging_calculator/README.rst
odoo/addons/stock_packaging_calculator/__init__.py
odoo/addons/stock_packaging_calculator/__manifest__.py
odoo/addons/stock_packaging_calculator/i18n/stock_packaging_calculator.pot
odoo/addons/stock_packaging_calculator/models/__init__.py
odoo/addons/stock_packaging_calculator/models/product.py
odoo/addons/stock_packaging_calculator/models/product_qty_by_packaging_mixin.py
odoo/addons/stock_packaging_calculator/readme/CONTRIBUTORS.rst
odoo/addons/stock_packaging_calculator/readme/DESCRIPTION.rst
odoo/addons/stock_packaging_calculator/readme/ROADMAP.rst
odoo/addons/stock_packaging_calculator/readme/USAGE.rst
odoo/addons/stock_packaging_calculator/static/description/icon.png
odoo/addons/stock_packaging_calculator/static/description/index.html
odoo/addons/stock_packaging_calculator/tests/__init__.py
odoo/addons/stock_packaging_calculator/tests/common.py
odoo/addons/stock_packaging_calculator/tests/test_packaging_calc.py
odoo/addons/stock_packaging_calculator/tests/test_pkg_qty_str.py
odoo/addons/stock_packaging_calculator/tests/utils.py
odoo13_addon_stock_packaging_calculator-13.0.1.9.1.dist-info/METADATA
odoo13_addon_stock_packaging_calculator-13.0.1.9.1.dist-info/WHEEL
odoo13_addon_stock_packaging_calculator-13.0.1.9.1.dist-info/top_level.txt
odoo13_addon_stock_packaging_calculator-13.0.1.9.1.dist-info/RECORD
